filesff/__init__.py
filesff/bz2s.py
filesff/caps.py
filesff/core/__init__.py
filesff/core/files.py
filesff/core/formatters.py
filesff/csvs.py
filesff/gzips.py
filesff/jsons.py
filesff/msgpacks.py
filesff/paths.py
filesff/pipes.py
filesff/protobufs.py
filesff/s3.py
filesff-0.0.7.dist-info/LICENSE
filesff-0.0.7.dist-info/METADATA
filesff-0.0.7.dist-info/WHEEL
filesff-0.0.7.dist-info/RECORD
