Metadata-Version: 2.1
Name: filesff
Version: 0.0.7
Summary: Files for Fun; Python Utilities
License: MIT
Author: Netanel Revah
Author-email: netanelrevah@outlook.com
Requires-Python: >=3.10,<4.0
Classifier: License :: OSI Approved :: MIT License
Classifier: Programming Language :: Python :: 3
Classifier: Programming Language :: Python :: 3.10
Classifier: Programming Language :: Python :: 3.11
Provides-Extra: cap
Provides-Extra: msgpack
Provides-Extra: protobuf
Provides-Extra: s3
Provides-Extra: ujson
Requires-Dist: boto3 (>=1.26.91,<2.0.0) ; extra == "s3"
Requires-Dist: cap (>=0.1.4,<0.2.0) ; extra == "cap"
Requires-Dist: msgpack (>=1.0.5,<2.0.0) ; extra == "msgpack"
Requires-Dist: protobuf (>=4.22.1,<5.0.0) ; extra == "protobuf"
Requires-Dist: ujson (>=5.6.0,<6.0.0) ; extra == "ujson"
